blazectl/__init__.py
blazectl/cli/__init__.py
blazectl/cli/cluster_cli.py
blazectl/cli/job_cli.py
blazectl/cli/kube_cli.py
blazectl/cli/main_cli.py
blazectl/cli/namespace_cli.py
blazectl/cli/workers_cli.py
blazectl/cluster/__init__.py
blazectl/cluster/aws_instance_types.json
blazectl/cluster/cluster.py
blazectl/commons/__init__.py
blazectl/commons/configuration.py
blazectl/commons/utils.py
blazectl/job/__init__.py
blazectl/job/job.py
blazectl/namespace/__init__.py
blazectl/namespace/config.py
blazectl/namespace/fsx_volume.py
blazectl/namespace/namespace.py
blazectl/namespace/provisioner.py
blazectl/namespace/roles.yaml
blazectl/namespace/service_account.py
blazectl/namespace/user-delete.sh
blazectl/namespace/user.sh
blazectl-0.5.1.dist-info/entry_points.txt
blazectl-0.5.1.dist-info/WHEEL
blazectl-0.5.1.dist-info/METADATA
blazectl-0.5.1.dist-info/RECORD
