Metadata-Version: 2.1
Name: blazectl
Version: 0.5.1
Summary: 
Author: Shailendra Sharma
Author-email: shailendra.sharma@gmail.com
Requires-Python: >=3.9,<4.0
Classifier: Programming Language :: Python :: 3
Classifier: Programming Language :: Python :: 3.9
Classifier: Programming Language :: Python :: 3.10
Classifier: Programming Language :: Python :: 3.11
Requires-Dist: dacite (>=1.6.0,<2.0.0)
Requires-Dist: dnspython (>=2.2.1,<3.0.0)
Requires-Dist: kubernetes (>=25.3.0,<26.0.0)
Requires-Dist: mysql-connector-python (>=8.0.32,<9.0.0)
Requires-Dist: pydantic (>=1.10.4,<2.0.0)
Requires-Dist: pyfiglet (>=0.8.post1,<0.9)
Requires-Dist: ray[default] (>=2.2.0,<3.0.0)
Requires-Dist: rich (>=12.6.0,<13.0.0)
Requires-Dist: shellingham (>=1.5.0.post1,<2.0.0)
Requires-Dist: typer (==0.7)
